pyyawl/__init__.py
pyyawl/cli.py
pyyawl/namedregistry.py
pyyawl/pyyawl.py
pyyawl/operators/__init__.py
pyyawl/operators/baseops.py
pyyawl/operators/bashops.py
pyyawl/operators/dvcops.py
pyyawl/operators/papermillops.py
pyyawl/operators/pythonops.py
pyyawl-0.4.0.dist-info/AUTHORS.rst
pyyawl-0.4.0.dist-info/LICENSE
pyyawl-0.4.0.dist-info/METADATA
pyyawl-0.4.0.dist-info/WHEEL
pyyawl-0.4.0.dist-info/entry_points.txt
pyyawl-0.4.0.dist-info/top_level.txt
pyyawl-0.4.0.dist-info/RECORD
