Metadata-Version: 2.1
Name: pyyawl
Version: 0.4.0
Summary: Yet another simple workflow language for python
Home-page: https://github.com/fabiofumarola/pyyawl
Author: Fabio Fumarola
Author-email: fabiofumarola@gmail.com
License: Apache Software License 2.0
Keywords: pyyawl
Platform: UNKNOWN
Classifier: Development Status :: 2 - Pre-Alpha
Classifier: Intended Audience :: Developers
Classifier: License :: OSI Approved :: Apache Software License
Classifier: Natural Language :: English
Classifier: Programming Language :: Python :: 3
Classifier: Programming Language :: Python :: 3.5
Classifier: Programming Language :: Python :: 3.6
Classifier: Programming Language :: Python :: 3.7
Classifier: Programming Language :: Python :: 3.8
Requires-Python: >=3.5
Requires-Dist: omegaconf (==2.0.2)
Requires-Dist: papermill (==2.2.0)
Requires-Dist: tqdm (==4.50.0)
